tf_hooks/__init__.py
tf_hooks/cleanup.py
tf_hooks/constants.py
tf_hooks/hooks.py
tf_hooks/register.py
tensorflow_hooks-1.0.0.dist-info/LICENSE
tensorflow_hooks-1.0.0.dist-info/METADATA
tensorflow_hooks-1.0.0.dist-info/WHEEL
tensorflow_hooks-1.0.0.dist-info/top_level.txt
tensorflow_hooks-1.0.0.dist-info/RECORD
