Metadata-Version: 2.1
Name: tensorflow-hooks
Version: 1.0.0
Summary: PyTorch-like hooks for TensorFlow Keras layers
Author: Craig Chan
Maintainer: Craig Chan
License: MIT License
Project-URL: Homepage, https://github.com/rachthree/tensorflow-hooks
Keywords: tensorflow,tf,keras,pytorch,torch,hooks,deep learning,machine learning,ml,neural network
Classifier: License :: OSI Approved :: MIT License
Classifier: Programming Language :: Python :: 3
Classifier: Programming Language :: Python :: 3.9
Classifier: Programming Language :: Python :: 3.10
Classifier: Programming Language :: Python :: 3.11
Requires-Python: >=3.9
License-File: LICENSE
Provides-Extra: dev
Requires-Dist: pre-commit ; extra == 'dev'
Provides-Extra: test
Requires-Dist: pytest ; extra == 'test'
Requires-Dist: safetensors ; extra == 'test'
